django_b2/__init__.py
django_b2/_version.py
django_b2/backblaze_b2.py
django_b2/storage.py
django_b2/tenant_storage.py
django_b2/.history/_version_20201104143028.py
django_b2/.history/_version_20201229162728.py
django_b2/.history/_version_20201229162913.py
django_b2/.history/backblaze_b2_20200528155630.py
django_b2/.history/backblaze_b2_20201229155017.py
django_b2/.history/backblaze_b2_20201229155127.py
django_b2/.history/backblaze_b2_20201229155150.py
django_b2/.history/backblaze_b2_20201229160136.py
django_b2/.history/backblaze_b2_20201229160829.py
django_b2/.history/backblaze_b2_20201229161424.py
django_b2/.history/backblaze_b2_20201229161543.py
django_b2/.history/storage_20201104130630.py
django_b2/.history/storage_20201229155623.py
django_b2/.history/storage_20201229160348.py
django_b2/.history/storage_20201229160907.py
django_b2/.history/storage_20201229160912.py
django_b2/.history/storage_20201229160915.py
django_b2/.history/storage_20201229161328.py
django_b2/management/commands/b2_clear_local_media.py
django_b2-0.7.0.data/scripts/pgtob2.sh
django_b2-0.7.0.dist-info/AUTHORS.rst
django_b2-0.7.0.dist-info/LICENSE
django_b2-0.7.0.dist-info/METADATA
django_b2-0.7.0.dist-info/WHEEL
django_b2-0.7.0.dist-info/top_level.txt
django_b2-0.7.0.dist-info/RECORD
