Metadata-Version: 2.1
Name: django-b2
Version: 0.7.0
Summary: django backblaze b2 storage using b2sdk
Home-page: https://github.com/pyutil/django-b2
Author: Mirek Zvolský
Author-email: zvolsky@seznam.cz
License: MIT
Download-URL: https://github.com/pyutil/django-b2/archive/0.7.0.tar.gz
Keywords: django-b2
Platform: UNKNOWN
Classifier: Development Status :: 4 - Beta
Classifier: Framework :: Django :: 1.11
Classifier: Framework :: Django :: 2.2
Classifier: Framework :: Django :: 3.0
Classifier: Intended Audience :: Developers
Classifier: License :: OSI Approved :: BSD License
Classifier: Natural Language :: English
Classifier: Programming Language :: Python :: 3
Classifier: Programming Language :: Python :: 3.6
Classifier: Programming Language :: Python :: 3.7
Classifier: Programming Language :: Python :: 3.8
Classifier: Programming Language :: Python :: 3.9
Requires-Dist: b2sdk (==1.0.2)
